[{"model": "order.product", "pk": 1, "fields": {"name": "Mobile Stand", "slug": "mobile-stand", "created_date": "2024-10-29T17:03:20.231Z"}}, {"model": "order.product", "pk": 2, "fields": {"name": "Key Ring", "slug": "key-ring", "created_date": "2024-10-30T06:13:48.273Z"}}, {"model": "order.product", "pk": 3, "fields": {"name": "NamePlate", "slug": "nameplate", "created_date": "2024-10-30T06:14:07.848Z"}}, {"model": "order.product", "pk": 4, "fields": {"name": "Tissue Box", "slug": "tissue-box", "created_date": "2024-10-30T06:14:44.159Z"}}, {"model": "order.product", "pk": 5, "fields": {"name": "Pen Holder", "slug": "pen-holder", "created_date": "2024-10-30T06:14:56.201Z"}}, {"model": "order.product", "pk": 6, "fields": {"name": "Bookmark", "slug": "bookmark", "created_date": "2024-10-30T06:15:17.128Z"}}, {"model": "order.product", "pk": 7, "fields": {"name": "Frame", "slug": "frame", "created_date": "2024-10-30T06:15:32.072Z"}}, {"model": "order.product", "pk": 8, "fields": {"name": "Tissue Holder", "slug": "tissue-holder", "created_date": "2024-10-30T06:15:53.311Z"}}, {"model": "order.product", "pk": 9, "fields": {"name": "Lamp Shade", "slug": "lamp-shade", "created_date": "2024-10-30T06:16:07.112Z"}}, {"model": "order.product", "pk": 10, "fields": {"name": "Diary", "slug": "diary", "created_date": "2024-10-30T06:16:19.272Z"}}, {"model": "order.product", "pk": 11, "fields": {"name": "Wall Clock", "slug": "wall-clock", "created_date": "2024-10-30T06:16:37.232Z"}}, {"model": "order.product", "pk": 12, "fields": {"name": "Name Tag", "slug": "name-tag", "created_date": "2024-10-30T06:16:57.943Z"}}, {"model": "order.product", "pk": 13, "fields": {"name": "Smart Table", "slug": "smart-table", "created_date": "2024-10-30T06:17:12.023Z"}}, {"model": "order.product", "pk": 14, "fields": {"name": "Start with", "slug": "start-with", "created_date": "2024-10-30T06:17:23.967Z"}}, {"model": "order.product", "pk": 15, "fields": {"name": "Table stand", "slug": "table-stand", "created_date": "2024-10-30T06:17:34.119Z"}}, {"model": "order.product", "pk": 16, "fields": {"name": "Card Holder", "slug": "card-holder", "created_date": "2024-10-30T06:17:48.503Z"}}, {"model": "order.product", "pk": 17, "fields": {"name": "Crest", "slug": "crest", "created_date": "2024-10-30T06:18:28.180Z"}}, {"model": "order.product", "pk": 18, "fields": {"name": "Comb", "slug": "comb", "created_date": "2024-10-30T12:25:52.508Z"}}]